pyenergyx/__init__.py
pyenergyx/pyenergyx.py
pyenergyx-0.2.dist-info/LICENSE
pyenergyx-0.2.dist-info/METADATA
pyenergyx-0.2.dist-info/WHEEL
pyenergyx-0.2.dist-info/top_level.txt
pyenergyx-0.2.dist-info/RECORD
