Metadata-Version: 2.1
Name: pyenergyx
Version: 0.2
Summary: A simple energy conversion library
Home-page: https://github.com/mariodgr/pyenergyx
Author: Mario David Gonzalez Ronda
Author-email: mariodgr@protonmail.com
Classifier: License :: OSI Approved :: MIT License
Classifier: Programming Language :: Python
Classifier: Programming Language :: Python :: 3
Classifier: Programming Language :: Python :: 3.6
Classifier: Programming Language :: Python :: 3.7
Classifier: Programming Language :: Python :: 3.8
Classifier: Programming Language :: Python :: 3.9
License-File: LICENSE
